[
	{
		"id": 0,
		"name": "archer",
		"spells": [5,10,2,7,3,8,0],
		"entitySpriteName": "archer",
		"melee": false,
		"maxHP": 100.0f,
		"movementSpeed": 5.0f,
		"attackPower": 12,
		"defense": 25,
		"unitExplanation": "An archer",
		"jumpAnimationFullTime":1,
		"teleportAnimationFullTime":1,
		"hurtAnimationFullTime":1,
		"attack2AnimationFullTime":1,
		"attackAnimationFullTime":1,
		"dieAnimationFullTime":1,
		"AppearAnimationFullTime":1,
		"idleAnimationSpeed": 0.1f,
		"castAnimationSpeed": 0.1f,
		"hurtAnimationSpeed": 0.1f,
		"dieAnimationSpeed": 0.1f,
		"moveAnimationSpeed": 0.1f,
		"teleportAnimationSpeed": 0.1f,
		"shootAnimationSpeed": 0.1f,
	}
]